Metadata-Version: 2.1
Name: fast-rest-framework
Version: 0.0.1
Summary: A fastapi framework
Home-page: https://github.com/Oceans594/fastapiframework
Author: Whliao
License: BSD License
Platform: all
Classifier: Programming Language :: Python
Classifier: Programming Language :: Python :: 3.8
License-File: LICENSE
